ckanext/__init__.py
ckanext/envidat_validators/__init__.py
ckanext/envidat_validators/__version__.py
ckanext/envidat_validators/logic.py
ckanext/envidat_validators/plugin.py
ckanext_envidat_validators-0.1.5.dist-info/entry_points.txt
ckanext_envidat_validators-0.1.5.dist-info/WHEEL
ckanext_envidat_validators-0.1.5.dist-info/METADATA
ckanext_envidat_validators-0.1.5.dist-info/licenses/LICENSE
ckanext_envidat_validators-0.1.5.dist-info/RECORD
