Metadata-Version: 2.1
Name: ckanext-envidat_validators
Version: 0.1.5
Summary: Custom CKAN validators for EnviDat.
License: MIT
Keywords: CKAN,validators,schema
Author-email: Sam Woodcock <sam.woodcock@protonmail.com>
Requires-Python: >=3.8
Classifier: Programming Language :: Python
Classifier: Programming Language :: Python :: 3 :: Only
Classifier: Programming Language :: Python :: 3.10
Classifier: Programming Language :: Python :: 3.8
Classifier: Programming Language :: Python :: 3.9
Classifier: Topic :: Utilities
Project-URL: documentation, https://envidat.gitlab-pages.wsl.ch/ckanext-envidat_validators
Project-URL: homepage, https://gitlabext.wsl.ch/EnviDat/ckanext-envidat_validators.git
Project-URL: repository, https://gitlabext.wsl.ch/EnviDat/ckanext-envidat_validators.git
